sopel_jisho/__init__.py
sopel_jisho/plugin.py
sopel_jisho-0.1.0.dist-info/COPYING
sopel_jisho-0.1.0.dist-info/METADATA
sopel_jisho-0.1.0.dist-info/WHEEL
sopel_jisho-0.1.0.dist-info/entry_points.txt
sopel_jisho-0.1.0.dist-info/top_level.txt
sopel_jisho-0.1.0.dist-info/RECORD
