Metadata-Version: 2.1
Name: sopel-jisho
Version: 0.1.0
Summary: Jisho lookup plugin for Sopel IRC bots.
Author-email: dgw <dgw@technobabbl.es>
License: GPL-3.0
Project-URL: Homepage, https://github.com/dgw/sopel-jisho
Project-URL: Bug Tracker, https://github.com/dgw/sopel-jisho/issues
Keywords: sopel,plugin,bot,irc
Platform: Linux x86, x86-64
Classifier: Development Status :: 4 - Beta
Classifier: Intended Audience :: Developers
Classifier: Intended Audience :: System Administrators
Classifier: License :: OSI Approved :: GNU General Public License v3 or later (GPLv3+)
Classifier: Topic :: Communications :: Chat :: Internet Relay Chat
Requires-Python: <4,>=3.8
License-File: COPYING
Requires-Dist: sopel >=8.0
